smlpy/__init__.py
smlpy/data_reader.py
smlpy/errors.py
smlpy/obis_t_kennzahlen.yaml
smlpy/sml_reader.py
smlpy/units.py
smlpy-0.2.3.dist-info/WHEEL
smlpy-0.2.3.dist-info/METADATA
smlpy-0.2.3.dist-info/RECORD
