Metadata-Version: 2.1
Name: smlpy
Version: 0.2.3
Summary: smlpy enables reading of smart meter language (sml) data from a smart power meter. You need a working IR-reading device for this, e.g. https://shop.weidmann-elektronik.de/index.php?page=product&info=24which must be connected to an USB port. Please note that this library only supports a small part of the SML-spec, especially the sending part is intentionally omitted
Home-page: https://github.com/ChristianSauer/smlpy
License: MIT
Keywords: sml,smart meter language,stromzähler,obis-t
Author: christian.sauer
Author-email: christian.sauer@codecentric.de
Requires-Python: >=3.7,<4.0
Classifier: Development Status :: 4 - Beta
Classifier: License :: OSI Approved :: MIT License
Classifier: Programming Language :: Python :: 3
Classifier: Programming Language :: Python :: 3.7
Classifier: Programming Language :: Python :: 3.8
Classifier: Programming Language :: Python :: 3.9
Classifier: Topic :: Home Automation
Requires-Dist: jsons (>=1.3.0,<2.0.0)
Requires-Dist: loguru (>=0.5.3,<0.6.0)
Requires-Dist: pyserial (>=3.5,<4.0)
Requires-Dist: pyserial-asyncio (>=0.5,<0.6)
Requires-Dist: pyyaml (>=5.3.1,<6.0.0)
Requires-Dist: typing-extensions (>=3.7.4,<4.0.0)
Project-URL: Repository, https://github.com/ChristianSauer/smlpy
